dbfilestorage/__init__.py
dbfilestorage/admin.py
dbfilestorage/models.py
dbfilestorage/storage.py
dbfilestorage/urls.py
dbfilestorage/views.py
dbfilestorage/migrations/0001_initial.py
dbfilestorage/migrations/0002_add_filehash_rename_files.py
dbfilestorage/migrations/0003_auto_remove_serialize.py
dbfilestorage/migrations/0004_dbfile_mtime.py
dbfilestorage/migrations/0005_auto_20170127_2037.py
dbfilestorage/migrations/0006_remove_dbfile_filehash.py
dbfilestorage/migrations/0007_auto_20170206_1940.py
dbfilestorage/migrations/0008_auto_20170206_1945.py
dbfilestorage/migrations/0009_auto_20170206_1954.py
dbfilestorage/migrations/0010_auto_20170206_1954.py
dbfilestorage/migrations/0011_auto_20170206_1956.py
dbfilestorage/migrations/0012_auto_20170206_2004.py
dbfilestorage/migrations/__init__.py
django_dbfilestorage-1.0.1.dist-info/METADATA
django_dbfilestorage-1.0.1.dist-info/RECORD
django_dbfilestorage-1.0.1.dist-info/WHEEL
django_dbfilestorage-1.0.1.dist-info/top_level.txt
