Metadata-Version: 2.1
Name: django-dbfilestorage
Version: 1.0.1
Summary: Database backed file storage for testing.
Home-page: https://gitlab.com/tyrelsouza/django-dbfilestorage
Author: Tyrel Souza
Author-email: tyrelsouza@gmail.com
License: MIT License
Download-URL: https://gitlab.com/tyrelsouza/django-dbfilestorage.git
Platform: UNKNOWN
Classifier: Operating System :: OS Independent
Classifier: Development Status :: 3 - Alpha
Classifier: Environment :: Web Environment
Classifier: Framework :: Django
Classifier: Intended Audience :: Developers
Classifier: License :: OSI Approved :: MIT License
Classifier: Programming Language :: Python :: 2
Classifier: Programming Language :: Python :: 3
Classifier: Topic :: Software Development :: Libraries :: Python Modules
Requires-Dist: Django (==1.11.10)
